wordflow/__init__.py
wordflow/cli/count.py
wordflow/cli/equal.py
wordflow/cli/frequency.py
wordflow/cli/length.py
wordflow/cli/lessthan.py
wordflow/cli/match.py
wordflow/cli/max.py
wordflow/cli/min.py
wordflow/cli/order.py
wordflow/cli/pluck.py
wordflow/cli/put.py
wordflow/cli/reverse.py
wordflow/cli/unique.py
wordflow/pipe_guard.py
wordflow-0.2.5.dist-info/METADATA
wordflow-0.2.5.dist-info/WHEEL
wordflow-0.2.5.dist-info/entry_points.txt
wordflow-0.2.5.dist-info/RECORD
