Metadata-Version: 2.3
Name: wordflow
Version: 0.2.5
Summary: 
Author: Chris Proctor
Author-email: github.com@accounts.chrisproctor.net
Requires-Python: >=3.10,<4.0
Classifier: Programming Language :: Python :: 3
Classifier: Programming Language :: Python :: 3.10
Classifier: Programming Language :: Python :: 3.11
Classifier: Programming Language :: Python :: 3.12
Classifier: Programming Language :: Python :: 3.13
Requires-Dist: wordfreq (>=3.1.1,<4.0.0)
